quackamollie/model/meta/langchain/__init__.py
quackamollie/model/meta/langchain/langchain_meta_model.py
quackamollie/model_manager/langchain/__init__.py
quackamollie/model_manager/langchain/langchain_model_manager.py
quackamollie/model_manager/langchain/helpers/__init__.py
quackamollie/model_manager/langchain/helpers/langchain_model_entry_point.py
quackamollie_langchain_model_manager-0.1.dist-info/LICENSE
quackamollie_langchain_model_manager-0.1.dist-info/METADATA
quackamollie_langchain_model_manager-0.1.dist-info/WHEEL
quackamollie_langchain_model_manager-0.1.dist-info/entry_points.txt
quackamollie_langchain_model_manager-0.1.dist-info/top_level.txt
quackamollie_langchain_model_manager-0.1.dist-info/RECORD
